{"cameraMode":{"drawMode":0,"name":"Shaded","section":"Shading Mode"},"sceneLighting":true,"audioPlay":false,"sceneViewState":{"m_AlwaysRefresh":false,"showFog":true,"showSkybox":true,"showFlares":true,"showImageEffects":true,"showParticleSystems":true,"showVisualEffectGraphs":true,"m_FxEnabled":true},"in2DMode":false,"pivot":{"x":3.8274118900299074,"y":-0.4011267423629761,"z":-19.384384155273439},"rotation":{"x":-0.08421002328395844,"y":0.0020903022959828378,"z":-0.00017552146164234728,"w":-0.9964507222175598},"size":5.658495903015137,"orthographic":false}